LICENSE
MANIFEST.in
README.md
droll-admin.py
setup.py
droll/__init__.py
droll.egg-info/PKG-INFO
droll.egg-info/SOURCES.txt
droll.egg-info/dependency_links.txt
droll.egg-info/requires.txt
droll.egg-info/top_level.txt
droll/access/__init__.py
droll/access/admin.py
droll/access/decorators.py
droll/access/forms.py
droll/access/models.py
droll/access/otp.py
droll/access/views.py
droll/access/migrations/0001_initial.py
droll/access/migrations/0002_auto_20160528_2108.py
droll/access/migrations/0003_user_otp_secret.py
droll/access/migrations/0004_user_two_fa_enabled.py
droll/access/migrations/__init__.py
droll/access/tests/__init__.py
droll/access/tests/factories.py
droll/access/tests/test_decorators.py
droll/access/tests/test_forms.py
droll/access/tests/test_models.py
droll/access/tests/test_otp.py
droll/access/tests/test_views.py
droll/application/__init__.py
droll/application/admin.py
droll/application/settings.py
droll/application/urls.py
droll/application/utils.py
droll/application/wsgi.py
droll/blog/__init__.py
droll/blog/admin.py
droll/blog/models.py
droll/blog/urls.py
droll/blog/views.py
droll/blog/migrations/0001_initial.py
droll/blog/migrations/0002_auto_20160703_1222.py
droll/blog/migrations/0003_link.py
droll/blog/migrations/0004_auto_20160723_2029.py
droll/blog/migrations/__init__.py
droll/blog/tests/__init__.py
droll/blog/tests/factories.py
droll/blog/tests/test_models.py
droll/blog/tests/test_views.py
droll/core/__init__.py
droll/core/admin.py
droll/core/context_processors.py
droll/core/models.py
droll/core/storage_backends.py
droll/core/views.py
droll/core/migrations/0001_initial.py
droll/core/migrations/__init__.py
droll/core/templatetags/__init__.py
droll/core/templatetags/markdown.py
droll/core/tests/__init__.py
droll/core/tests/factories.py
droll/core/tests/test_context_processors.py
droll/core/tests/test_models.py
droll/core/tests/test_storage_backends.py
droll/core/tests/test_templatetags.py
droll/core/tests/utils.py
droll/static/admin/css/otp.css
droll/static/local/css/main.css
droll/static/local/css/noto.css
droll/static/local/css/opensans.css
droll/static/vendor/highlight/CHANGES.md
