Metadata-Version: 1.1
Name: droll
Version: 0.1.dev1
Summary: Code-friendly blogging platform
Home-page: https://github.com/node13h/droll
Author: Sergej Alikov
Author-email: sergej.alikov@gmail.com
License: AGPL-3.0
Keywords: django blog
Platform: UNKNOWN
Classifier: Development Status :: 3 - Alpha
Classifier: Intended Audience :: Developers
Classifier: Framework :: Django :: 1.8
Classifier: Topic :: Software Development :: Build Tools
Classifier: License :: OSI Approved :: MIT License
Classifier: License :: OSI Approved :: GNU Affero General Public License v3
Classifier: Programming Language :: Python :: 3
